{
  "editor.formatOnSave": true,
  "rust-analyzer.diagnostics.experimental.enable": true,
  "[rust]": {
    "editor.defaultFormatter": "rust-lang.rust-analyzer"
  },
  "[starlark]": {
    "editor.defaultFormatter": "BazelBuild.vscode-bazel"
  },
  "bazel.executable": "bazel",
  "bazel.buildifierExecutable": "__BUILDIFIER_PATH__",
  "bazel.lsp.command": "starpls",
  "bazel.lsp.args": [
    "server",
    "--experimental_enable_label_completions",
    "--experimental_use_code_flow_analysis",
    "--experimental_infer_ctx_attributes"
  ],
  "rust-analyzer.rustfmt.overrideCommand": [
    "__RUSTFMT_PATH__",
    "--style-edition",
    "2024",
    "--emit",
    "stdout",
    "--config-path",
    "__WORKSPACE_ROOT__/rustfmt.toml"
  ],
  "rust-analyzer.check.overrideCommand": [
    "__WORKSPACE_ROOT__/tools/vscode/rust-analyzer-check.bash",
    "{label}"
  ],
  "rust-analyzer.server.path": "__RUST_ANALYZER_PATH__",
  "rust-analyzer.workspace.discoverConfig": {
    "command": [
      "__WORKSPACE_ROOT__/tools/rust-analyzer/project-config.bash",
      "{arg}"
    ],
    "progressLabel": "rust_analyzer",
    "filesToWatch": [
      "BUILD",
      "BUILD.bazel",
      "MODULE.bazel"
    ]
  }
}